waterz/frontend_agglomerate.h
waterz/evaluate.cpp
waterz/evaluate.cpython-35m-x86_64-linux-gnu.so
waterz/evaluate.pyx
waterz/frontend_evaluate.h
waterz/frontend_evaluate.cpp
waterz/agglomerate.pyx
waterz/__init__.py
waterz/frontend_agglomerate.cpp
waterz/backend/ConstantProvider.hpp
waterz/backend/basic_watershed.hpp
waterz/backend/Histogram.hpp
waterz/backend/BinQueue.hpp
waterz/backend/RandomNumberProvider.hpp
waterz/backend/PriorityQueue.hpp
waterz/backend/RegionSizeProvider.hpp
waterz/backend/VectorQuantileProvider.hpp
waterz/backend/RegionGraph.hpp
waterz/backend/CompoundProvider.hpp
waterz/backend/region_graph.hpp
waterz/backend/StatisticsProvider.hpp
waterz/backend/types.hpp
waterz/backend/ContactAreaProvider.hpp
waterz/backend/MergeProviders.hpp
waterz/backend/IterativeRegionMerging.hpp
waterz/backend/Operators.hpp
waterz/backend/MeanAffinityProvider.hpp
waterz/backend/evaluate.hpp
waterz/backend/MergeFunctions.hpp
waterz/backend/MaxKAffinityProvider.hpp
waterz/backend/MinAffinityProvider.hpp
waterz/backend/MaxKValues.hpp
waterz/backend/HistogramQuantileProvider.hpp
waterz/backend/discretize.hpp
waterz/backend/MaxAffinityProvider.hpp
waterz-0.9.4.dist-info/top_level.txt
waterz-0.9.4.dist-info/RECORD
waterz-0.9.4.dist-info/METADATA
waterz-0.9.4.dist-info/WHEEL
