Metadata-Version: 2.1
Name: waterz
Version: 0.9.4
Summary: Simple watershed and agglomeration for affinity graphs.
Home-page: https://github.com/funkey/waterz
Author: Jan Funke, Jingpeng Wu
Author-email: jfunke@iri.upc.edu
License: MIT
Platform: UNKNOWN
Classifier: Programming Language :: Python :: 3
Classifier: Intended Audience :: Developers
Classifier: License :: OSI Approved :: MIT License
Classifier: Operating System :: OS Independent
Requires-Dist: numpy
Requires-Dist: cython
